chromadb_semantic.py
chromadb_semantic-1.0.3.dist-info/METADATA
chromadb_semantic-1.0.3.dist-info/WHEEL
chromadb_semantic-1.0.3.dist-info/entry_points.txt
chromadb_semantic-1.0.3.dist-info/top_level.txt
chromadb_semantic-1.0.3.dist-info/RECORD
